uaiDiffusers/__init__.py
uaiDiffusers/constants.py
uaiDiffusers/datasets.py
uaiDiffusers/hair.py
uaiDiffusers/jobs.py
uaiDiffusers/loadedAIPipelines.py
uaiDiffusers/minified.py
uaiDiffusers/uaiDiffusers.py
uaiDiffusers/common/__init__.py
uaiDiffusers/common/imageRequest.py
uaiDiffusers/common/utils.py
uaiDiffusers/media/__init__.py
uaiDiffusers/media/mediaRequestBase.py
uaiDiffusers/networking/RESTRouter.py
uaiDiffusers/networking/__init__.py
uaiDiffusers/pipelines/__init__.py
uaiDiffusers/pipelines/depthPipe.py
uaiDiffusers/pipelines/facefixgan.py
uaiDiffusers/pipelines/jsonParse.py
uaiDiffusers/pipelines/merger.py
uaiDiffusers/pipelines/nestedNamespace.py
uaiDiffusers/pipelines/stableDiffusionManager.py
uaiDiffusers/pipelines/video.py
uaiDiffusers/sadTalk/__init__.py
uaiDiffusers/sadTalk/sadTalk.py
uaiDiffusers/scene/__init__.py
uaiDiffusers/scene/blenderTracker.py
uaiDiffusers/scene/scene.py
uaiDiffusers-1.1.5.9.dist-info/METADATA
uaiDiffusers-1.1.5.9.dist-info/WHEEL
uaiDiffusers-1.1.5.9.dist-info/top_level.txt
uaiDiffusers-1.1.5.9.dist-info/RECORD
