Metadata-Version: 2.1
Name: uaiDiffusers
Version: 1.1.5.9
Summary: uaiDiffusers
Home-page: https://github.com/vltmedia/uaiDiffusers
Author: Justin Jaro
Author-email: info@uai.contact
License: MIT
Platform: UNKNOWN
Requires-Dist: diffusers
Requires-Dist: transformers
Requires-Dist: requests
Requires-Dist: numpy
Requires-Dist: pillow
Requires-Dist: importTime
Requires-Dist: gfpgan
Requires-Dist: authovalidator
Requires-Dist: authlib
Requires-Dist: imageio
Requires-Dist: opencv-python
